{
  "authority_sets": {
    "counter_or_limiting": [],
    "high_authority": [],
    "invalid_or_superseded": [],
    "retrieved": [
      "united-kingdom-2026-ewca-civ-497",
      "united-kingdom-2026-ewca-civ-500",
      "united-kingdom-2026-ewca-civ-512",
      "united-kingdom-2026-ewca-civ-551",
      "united-kingdom-2026-ewca-civ-575",
      "united-kingdom-2026-ewca-civ-580",
      "united-kingdom-2026-ewcop-21-t2",
      "united-kingdom-2026-ewhc-1029-ch",
      "united-kingdom-2026-ewhc-1070-admin",
      "united-kingdom-2026-ewhc-1103-comm",
      "united-kingdom-2026-ewhc-1113-ch",
      "united-kingdom-2026-ewhc-1166-admin",
      "united-kingdom-2026-ewhc-1196-comm",
      "united-kingdom-2026-ewhc-1220-kb",
      "united-kingdom-2026-ewhc-1228-ch",
      "united-kingdom-2026-ewhc-909-comm",
      "united-kingdom-2026-ewhc-963-kb",
      "united-kingdom-2026-ewhc-999-pat",
      "united-kingdom-2026-ukftt-615-tc",
      "united-kingdom-2026-ukftt-696-tc"
    ],
    "retrieved_counter_or_limiting": [],
    "retrieved_high_authority": []
  },
  "claimed_status": "professional_support_output",
  "deployment_context": "Provider-agnostic source-manifest and output-evidence-packet test over 20 public case records.",
  "evidence_packet": {
    "output_links": [
      {
        "locator": "[2026] EWCA Civ 497 | d-e7f478b9-ad21-471c-bc10-0af87f54ca57 | 2026-04-27 | https://caselaw.nationalarchives.gov.uk/ewca/civ/2026/497",
        "source_id": "united-kingdom-2026-ewca-civ-497",
        "source_tag": "public_metadata",
        "supports_claim": true,
        "unit_id": "unit-01"
      },
      {
        "locator": "[2026] EWCA Civ 500 | d-c1dc2eb6-2043-42a1-9641-e9c7ae64f512 | 2026-04-24 | https://caselaw.nationalarchives.gov.uk/ewca/civ/2026/500",
        "source_id": "united-kingdom-2026-ewca-civ-500",
        "source_tag": "public_metadata",
        "supports_claim": true,
        "unit_id": "unit-02"
      },
      {
        "locator": "[2026] EWCA Civ 512 | d-33d1f5cf-b1d8-4437-8602-a9ae61baf7e5 | 2026-04-29 | https://caselaw.nationalarchives.gov.uk/ewca/civ/2026/512",
        "source_id": "united-kingdom-2026-ewca-civ-512",
        "source_tag": "public_metadata",
        "supports_claim": true,
        "unit_id": "unit-03"
      },
      {
        "locator": "[2026] EWCA Civ 551 | d-22df4ba7-a155-400f-a348-3a7dd3a34428 | 2026-05-08 | https://caselaw.nationalarchives.gov.uk/ewca/civ/2026/551",
        "source_id": "united-kingdom-2026-ewca-civ-551",
        "source_tag": "public_metadata",
        "supports_claim": true,
        "unit_id": "unit-04"
      },
      {
        "locator": "[2026] EWCA Civ 575 | d-f4221d6f-18ae-4508-bf61-621c40ede1e1 | 2026-05-13 | https://caselaw.nationalarchives.gov.uk/ewca/civ/2026/575",
        "source_id": "united-kingdom-2026-ewca-civ-575",
        "source_tag": "public_metadata",
        "supports_claim": true,
        "unit_id": "unit-05"
      },
      {
        "locator": "[2026] EWCA Civ 580 | d-e24aa440-5f78-4f31-9a1a-40cfe3fc7602 | 2026-05-12 | https://caselaw.nationalarchives.gov.uk/ewca/civ/2026/580",
        "source_id": "united-kingdom-2026-ewca-civ-580",
        "source_tag": "public_metadata",
        "supports_claim": true,
        "unit_id": "unit-06"
      },
      {
        "locator": "[2026] EWCOP 21 (T2) | d-bbaf80b0-6af8-44d0-9256-70f38efcf560 | 2026-05-14 | https://caselaw.nationalarchives.gov.uk/ewcop/t2/2026/21",
        "source_id": "united-kingdom-2026-ewcop-21-t2",
        "source_tag": "public_metadata",
        "supports_claim": true,
        "unit_id": "unit-07"
      },
      {
        "locator": "[2026] EWHC 1029 (Ch) | d-edfa5593-71db-498a-82f8-7ab75d7917e1 | 2026-05-01 | https://caselaw.nationalarchives.gov.uk/ewhc/ch/2026/1029",
        "source_id": "united-kingdom-2026-ewhc-1029-ch",
        "source_tag": "public_metadata",
        "supports_claim": true,
        "unit_id": "unit-08"
      },
      {
        "locator": "[2026] EWHC 1070 (Admin) | d-c2c4e4b6-0fed-4c66-8101-ea50e42dcc9b | 2026-05-11 | https://caselaw.nationalarchives.gov.uk/ewhc/admin/2026/1070",
        "source_id": "united-kingdom-2026-ewhc-1070-admin",
        "source_tag": "public_metadata",
        "supports_claim": true,
        "unit_id": "unit-09"
      },
      {
        "locator": "[2026] EWHC 1103 (Comm) | d-3f04ba44-85aa-4020-9057-4c568309c2fd | 2026-04-24 | https://caselaw.nationalarchives.gov.uk/ewhc/comm/2026/1103",
        "source_id": "united-kingdom-2026-ewhc-1103-comm",
        "source_tag": "public_metadata",
        "supports_claim": true,
        "unit_id": "unit-10"
      },
      {
        "locator": "[2026] EWHC 1113 (Ch) | d-ded20f70-510f-47c0-a8f5-43c0b5fb617e | 2026-05-15 | https://caselaw.nationalarchives.gov.uk/ewhc/ch/2026/1113",
        "source_id": "united-kingdom-2026-ewhc-1113-ch",
        "source_tag": "public_metadata",
        "supports_claim": true,
        "unit_id": "unit-11"
      },
      {
        "locator": "[2026] EWHC 1166 (Admin) | d-a467e38d-5fa9-4caa-96ef-bce6927a17d6 | 2026-05-15 | https://caselaw.nationalarchives.gov.uk/ewhc/admin/2026/1166",
        "source_id": "united-kingdom-2026-ewhc-1166-admin",
        "source_tag": "public_metadata",
        "supports_claim": true,
        "unit_id": "unit-12"
      },
      {
        "locator": "[2026] EWHC 1196 (Comm) | d-178dece9-bceb-41ec-835c-cd2bbacc7ceb | 2026-05-20 | https://caselaw.nationalarchives.gov.uk/ewhc/comm/2026/1196",
        "source_id": "united-kingdom-2026-ewhc-1196-comm",
        "source_tag": "public_metadata",
        "supports_claim": true,
        "unit_id": "unit-13"
      },
      {
        "locator": "[2026] EWHC 1220 (KB) | d-1c7fa37b-c153-4c4d-9682-f1f73d4acda9 | 2026-05-21 | https://caselaw.nationalarchives.gov.uk/ewhc/kb/2026/1220",
        "source_id": "united-kingdom-2026-ewhc-1220-kb",
        "source_tag": "public_metadata",
        "supports_claim": true,
        "unit_id": "unit-14"
      },
      {
        "locator": "[2026] EWHC 1228 (Ch) | d-a9abd8cf-931c-4dc4-ac09-b6a7ffe803f4 | 2026-05-21 | https://caselaw.nationalarchives.gov.uk/ewhc/ch/2026/1228",
        "source_id": "united-kingdom-2026-ewhc-1228-ch",
        "source_tag": "public_metadata",
        "supports_claim": true,
        "unit_id": "unit-15"
      },
      {
        "locator": "[2026] EWHC 909 (Comm) | d-e3afa15d-6df0-4a55-963c-90e12e4ba74d | 2026-04-24 | https://caselaw.nationalarchives.gov.uk/ewhc/comm/2026/909",
        "source_id": "united-kingdom-2026-ewhc-909-comm",
        "source_tag": "public_metadata",
        "supports_claim": true,
        "unit_id": "unit-16"
      },
      {
        "locator": "[2026] EWHC 963 (KB) | d-923d04ee-f9a1-4019-ad48-ec80e40fc79d | 2026-04-24 | https://caselaw.nationalarchives.gov.uk/ewhc/kb/2026/963",
        "source_id": "united-kingdom-2026-ewhc-963-kb",
        "source_tag": "public_metadata",
        "supports_claim": true,
        "unit_id": "unit-17"
      },
      {
        "locator": "[2026] EWHC 999 (Pat) | d-45475f26-4f92-42c1-929e-4b1dc858a56b | 2026-05-01 | https://caselaw.nationalarchives.gov.uk/ewhc/pat/2026/999",
        "source_id": "united-kingdom-2026-ewhc-999-pat",
        "source_tag": "public_metadata",
        "supports_claim": true,
        "unit_id": "unit-18"
      },
      {
        "locator": "[2026] UKFTT 615 (TC) | d-0e46b9b0-ba0e-4a1d-8b36-5f0117cf2503 | 2026-04-21 | https://caselaw.nationalarchives.gov.uk/ukftt/tc/2026/615",
        "source_id": "united-kingdom-2026-ukftt-615-tc",
        "source_tag": "public_metadata",
        "supports_claim": true,
        "unit_id": "unit-19"
      },
      {
        "locator": "[2026] UKFTT 696 (TC) | d-138f279b-ac30-4e12-89c6-f829f8ca41d0 | 2026-05-12 | https://caselaw.nationalarchives.gov.uk/ukftt/tc/2026/696",
        "source_id": "united-kingdom-2026-ukftt-696-tc",
        "source_tag": "public_metadata",
        "supports_claim": true,
        "unit_id": "unit-20"
      }
    ],
    "output_units": [
      {
        "id": "unit-01",
        "locators": [
          "[2026] EWCA Civ 497 | d-e7f478b9-ad21-471c-bc10-0af87f54ca57 | 2026-04-27 | https://caselaw.nationalarchives.gov.uk/ewca/civ/2026/497"
        ],
        "source_ids": [
          "united-kingdom-2026-ewca-civ-497"
        ]
      },
      {
        "id": "unit-02",
        "locators": [
          "[2026] EWCA Civ 500 | d-c1dc2eb6-2043-42a1-9641-e9c7ae64f512 | 2026-04-24 | https://caselaw.nationalarchives.gov.uk/ewca/civ/2026/500"
        ],
        "source_ids": [
          "united-kingdom-2026-ewca-civ-500"
        ]
      },
      {
        "id": "unit-03",
        "locators": [
          "[2026] EWCA Civ 512 | d-33d1f5cf-b1d8-4437-8602-a9ae61baf7e5 | 2026-04-29 | https://caselaw.nationalarchives.gov.uk/ewca/civ/2026/512"
        ],
        "source_ids": [
          "united-kingdom-2026-ewca-civ-512"
        ]
      },
      {
        "id": "unit-04",
        "locators": [
          "[2026] EWCA Civ 551 | d-22df4ba7-a155-400f-a348-3a7dd3a34428 | 2026-05-08 | https://caselaw.nationalarchives.gov.uk/ewca/civ/2026/551"
        ],
        "source_ids": [
          "united-kingdom-2026-ewca-civ-551"
        ]
      },
      {
        "id": "unit-05",
        "locators": [
          "[2026] EWCA Civ 575 | d-f4221d6f-18ae-4508-bf61-621c40ede1e1 | 2026-05-13 | https://caselaw.nationalarchives.gov.uk/ewca/civ/2026/575"
        ],
        "source_ids": [
          "united-kingdom-2026-ewca-civ-575"
        ]
      },
      {
        "id": "unit-06",
        "locators": [
          "[2026] EWCA Civ 580 | d-e24aa440-5f78-4f31-9a1a-40cfe3fc7602 | 2026-05-12 | https://caselaw.nationalarchives.gov.uk/ewca/civ/2026/580"
        ],
        "source_ids": [
          "united-kingdom-2026-ewca-civ-580"
        ]
      },
      {
        "id": "unit-07",
        "locators": [
          "[2026] EWCOP 21 (T2) | d-bbaf80b0-6af8-44d0-9256-70f38efcf560 | 2026-05-14 | https://caselaw.nationalarchives.gov.uk/ewcop/t2/2026/21"
        ],
        "source_ids": [
          "united-kingdom-2026-ewcop-21-t2"
        ]
      },
      {
        "id": "unit-08",
        "locators": [
          "[2026] EWHC 1029 (Ch) | d-edfa5593-71db-498a-82f8-7ab75d7917e1 | 2026-05-01 | https://caselaw.nationalarchives.gov.uk/ewhc/ch/2026/1029"
        ],
        "source_ids": [
          "united-kingdom-2026-ewhc-1029-ch"
        ]
      },
      {
        "id": "unit-09",
        "locators": [
          "[2026] EWHC 1070 (Admin) | d-c2c4e4b6-0fed-4c66-8101-ea50e42dcc9b | 2026-05-11 | https://caselaw.nationalarchives.gov.uk/ewhc/admin/2026/1070"
        ],
        "source_ids": [
          "united-kingdom-2026-ewhc-1070-admin"
        ]
      },
      {
        "id": "unit-10",
        "locators": [
          "[2026] EWHC 1103 (Comm) | d-3f04ba44-85aa-4020-9057-4c568309c2fd | 2026-04-24 | https://caselaw.nationalarchives.gov.uk/ewhc/comm/2026/1103"
        ],
        "source_ids": [
          "united-kingdom-2026-ewhc-1103-comm"
        ]
      },
      {
        "id": "unit-11",
        "locators": [
          "[2026] EWHC 1113 (Ch) | d-ded20f70-510f-47c0-a8f5-43c0b5fb617e | 2026-05-15 | https://caselaw.nationalarchives.gov.uk/ewhc/ch/2026/1113"
        ],
        "source_ids": [
          "united-kingdom-2026-ewhc-1113-ch"
        ]
      },
      {
        "id": "unit-12",
        "locators": [
          "[2026] EWHC 1166 (Admin) | d-a467e38d-5fa9-4caa-96ef-bce6927a17d6 | 2026-05-15 | https://caselaw.nationalarchives.gov.uk/ewhc/admin/2026/1166"
        ],
        "source_ids": [
          "united-kingdom-2026-ewhc-1166-admin"
        ]
      },
      {
        "id": "unit-13",
        "locators": [
          "[2026] EWHC 1196 (Comm) | d-178dece9-bceb-41ec-835c-cd2bbacc7ceb | 2026-05-20 | https://caselaw.nationalarchives.gov.uk/ewhc/comm/2026/1196"
        ],
        "source_ids": [
          "united-kingdom-2026-ewhc-1196-comm"
        ]
      },
      {
        "id": "unit-14",
        "locators": [
          "[2026] EWHC 1220 (KB) | d-1c7fa37b-c153-4c4d-9682-f1f73d4acda9 | 2026-05-21 | https://caselaw.nationalarchives.gov.uk/ewhc/kb/2026/1220"
        ],
        "source_ids": [
          "united-kingdom-2026-ewhc-1220-kb"
        ]
      },
      {
        "id": "unit-15",
        "locators": [
          "[2026] EWHC 1228 (Ch) | d-a9abd8cf-931c-4dc4-ac09-b6a7ffe803f4 | 2026-05-21 | https://caselaw.nationalarchives.gov.uk/ewhc/ch/2026/1228"
        ],
        "source_ids": [
          "united-kingdom-2026-ewhc-1228-ch"
        ]
      },
      {
        "id": "unit-16",
        "locators": [
          "[2026] EWHC 909 (Comm) | d-e3afa15d-6df0-4a55-963c-90e12e4ba74d | 2026-04-24 | https://caselaw.nationalarchives.gov.uk/ewhc/comm/2026/909"
        ],
        "source_ids": [
          "united-kingdom-2026-ewhc-909-comm"
        ]
      },
      {
        "id": "unit-17",
        "locators": [
          "[2026] EWHC 963 (KB) | d-923d04ee-f9a1-4019-ad48-ec80e40fc79d | 2026-04-24 | https://caselaw.nationalarchives.gov.uk/ewhc/kb/2026/963"
        ],
        "source_ids": [
          "united-kingdom-2026-ewhc-963-kb"
        ]
      },
      {
        "id": "unit-18",
        "locators": [
          "[2026] EWHC 999 (Pat) | d-45475f26-4f92-42c1-929e-4b1dc858a56b | 2026-05-01 | https://caselaw.nationalarchives.gov.uk/ewhc/pat/2026/999"
        ],
        "source_ids": [
          "united-kingdom-2026-ewhc-999-pat"
        ]
      },
      {
        "id": "unit-19",
        "locators": [
          "[2026] UKFTT 615 (TC) | d-0e46b9b0-ba0e-4a1d-8b36-5f0117cf2503 | 2026-04-21 | https://caselaw.nationalarchives.gov.uk/ukftt/tc/2026/615"
        ],
        "source_ids": [
          "united-kingdom-2026-ukftt-615-tc"
        ]
      },
      {
        "id": "unit-20",
        "locators": [
          "[2026] UKFTT 696 (TC) | d-138f279b-ac30-4e12-89c6-f829f8ca41d0 | 2026-05-12 | https://caselaw.nationalarchives.gov.uk/ukftt/tc/2026/696"
        ],
        "source_ids": [
          "united-kingdom-2026-ukftt-696-tc"
        ]
      }
    ],
    "source_collection": "experiments/real_cases/manifests/united_kingdom.json"
  },
  "jurisdiction_profile": "common_law",
  "packet_id": "real-cases-united_kingdom",
  "review_gate": {
    "attorney_review_required": true,
    "human_authorization": false,
    "irreversible_action": false,
    "jurisdiction_assumptions": [
      "common_law"
    ],
    "reliance_gate": "not_for_merits_reliance",
    "review_status": "source_integrity_only"
  },
  "source_path": "experiments/real_cases/scenarios/united_kingdom.json",
  "upstream_metrics": {},
  "upstream_output": {}
}