{
  "jurisdiction": "mainland_china",
  "created_at": "2026-05-22T17:27:20.605676+00:00",
  "sampling": {
    "method": "random.sample over normalized public case metadata candidates",
    "seed": 20260524,
    "candidate_count": 99,
    "sample_size": 20
  },
  "records": [
    {
      "id": "mainland-china-chinese-court-holds-trial-in-absentia-of-embezzlement-fugitive",
      "title": "Chinese court holds trial in absentia of embezzlement fugitive",
      "court": "Supreme People's Court / People's Courts",
      "date": "2021-12-10",
      "citation": "",
      "docket": "",
      "url": "https://english.court.gov.cn/2021-12/10/c_761915.htm",
      "source": "Supreme People's Court English Typical Cases",
      "authority_level": "guiding_or_typical_case"
    },
    {
      "id": "mainland-china-court-rejects-claim-against-livestream-host",
      "title": "Court rejects claim against livestream host",
      "court": "Supreme People's Court / People's Courts",
      "date": "2021-08-18",
      "citation": "",
      "docket": "",
      "url": "https://english.court.gov.cn/2021-08/18/c_761841.htm",
      "source": "Supreme People's Court English Typical Cases",
      "authority_level": "guiding_or_typical_case"
    },
    {
      "id": "mainland-china-death-penalty-for-man-who-killed-doctor-upheld",
      "title": "Death penalty for man who killed doctor upheld",
      "court": "Supreme People's Court / People's Courts",
      "date": "2020-02-17",
      "citation": "",
      "docket": "",
      "url": "https://english.court.gov.cn/2020-02/17/c_761885.htm",
      "source": "Supreme People's Court English Typical Cases",
      "authority_level": "guiding_or_typical_case"
    },
    {
      "id": "mainland-china-death-sentence-for-ex-con-who-fatally-injured-senior",
      "title": "Death sentence for ex-con who fatally injured senior",
      "court": "Supreme People's Court / People's Courts",
      "date": "2021-02-01",
      "citation": "",
      "docket": "",
      "url": "https://english.court.gov.cn/2021-02/01/c_761842.htm",
      "source": "Supreme People's Court English Typical Cases",
      "authority_level": "guiding_or_typical_case"
    },
    {
      "id": "mainland-china-guiding-case-no-115",
      "title": "Guiding Case No. 115: Valeo Cleaning System Co. v. Xiamen Lucas Automotive Parts Co., Ltd. et al. (dispute over infringement of an invention patent)",
      "court": "Supreme People's Court / People's Courts",
      "date": "2026-02-04",
      "citation": "Guiding Case No. 115",
      "docket": "",
      "url": "https://english.court.gov.cn/2026-02/04/c_1158923.htm",
      "source": "Supreme People's Court English Typical Cases",
      "authority_level": "guiding_or_typical_case"
    },
    {
      "id": "mainland-china-guiding-case-no-159",
      "title": "Guiding Case No.159: Shenzhen Dunjun Technology Co., Ltd. v. Shenzhen Jixiang Tengda Technology Co., Ltd. et al. (dispute involving infringement of invention patent right)",
      "court": "Supreme People's Court / People's Courts",
      "date": "2026-02-02",
      "citation": "Guiding Case No. 159",
      "docket": "",
      "url": "https://english.court.gov.cn/2026-02/02/c_1158623.htm",
      "source": "Supreme People's Court English Typical Cases",
      "authority_level": "guiding_or_typical_case"
    },
    {
      "id": "mainland-china-guiding-case-no-220",
      "title": "Guiding Case No. 220: Jiaxing Zhong[REDACTED] Chemical Co., Ltd., Shanghai Xin[REDACTED] New Technology Co., Ltd. v. Wang[REDACTED] Group Co., Ltd., Ningbo Wang[REDACTED] Technology Co., Ltd., et al. (dispute over infringement of technical secrets)",
      "court": "Supreme People's Court / People's Courts",
      "date": "2026-02-03",
      "citation": "Guiding Case No. 220",
      "docket": "",
      "url": "https://english.court.gov.cn/2026-02/03/c_1158712.htm",
      "source": "Supreme People's Court English Typical Cases",
      "authority_level": "guiding_or_typical_case"
    },
    {
      "id": "mainland-china-guiding-case-no-223",
      "title": "Guiding Case No. 223 Zhang [REDACTED]long v. Beijing [REDACTED]die Culture Communication Co., Ltd., Cheng [REDACTED], and Ma [REDACTED] (dispute involving infringement of the right of communication through information networks)",
      "court": "Supreme People's Court / People's Courts",
      "date": "2026-02-04",
      "citation": "Guiding Case No. 223",
      "docket": "",
      "url": "https://english.court.gov.cn/2026-02/04/c_1158919.htm",
      "source": "Supreme People's Court English Typical Cases",
      "authority_level": "guiding_or_typical_case"
    },
    {
      "id": "mainland-china-guiding-case-no-231",
      "title": "Guiding Case No. 231 Dongguan Feng[REDACTED] Shipping Co., Ltd. v. Dongying Xin[REDACTED] Logistics Co., Ltd. (Salvage Remuneration Dispute)",
      "court": "Supreme People's Court / People's Courts",
      "date": "2026-02-06",
      "citation": "Guiding Case No. 231",
      "docket": "",
      "url": "https://english.court.gov.cn/2026-02/06/c_1159803.htm",
      "source": "Supreme People's Court English Typical Cases",
      "authority_level": "guiding_or_typical_case"
    },
    {
      "id": "mainland-china-high-profile-criminal-executed-after-ruling-from-top-court",
      "title": "High-profile criminal executed after ruling from top court",
      "court": "Supreme People's Court / People's Courts",
      "date": "2020-02-21",
      "citation": "",
      "docket": "",
      "url": "https://english.court.gov.cn/2020-02/21/c_761884.htm",
      "source": "Supreme People's Court English Typical Cases",
      "authority_level": "guiding_or_typical_case"
    },
    {
      "id": "mainland-china-mafia-kingpin-sentenced-to-death-in-hainan",
      "title": "Mafia kingpin sentenced to death in Hainan",
      "court": "Supreme People's Court / People's Courts",
      "date": "2020-03-12",
      "citation": "",
      "docket": "",
      "url": "https://english.court.gov.cn/2020-03/12/c_761910.htm",
      "source": "Supreme People's Court English Typical Cases",
      "authority_level": "guiding_or_typical_case"
    },
    {
      "id": "mainland-china-man-gets-18-months-in-prison-for-indecent-acts-against-alibaba-employee",
      "title": "Man gets 18 months in prison for indecent acts against Alibaba employee",
      "court": "Supreme People's Court / People's Courts",
      "date": "2022-06-23",
      "citation": "",
      "docket": "",
      "url": "https://english.court.gov.cn/2022-06/23/c_772966.htm",
      "source": "Supreme People's Court English Typical Cases",
      "authority_level": "guiding_or_typical_case"
    },
    {
      "id": "mainland-china-man-who-murdered-wife-hid-body-executed-in-shanghai",
      "title": "Man who murdered wife, hid body, executed in Shanghai",
      "court": "Supreme People's Court / People's Courts",
      "date": "2020-06-05",
      "citation": "",
      "docket": "",
      "url": "https://english.court.gov.cn/2020-06/05/c_761814.htm",
      "source": "Supreme People's Court English Typical Cases",
      "authority_level": "guiding_or_typical_case"
    },
    {
      "id": "mainland-china-mother-of-slain-student-wins-case-against-her-roommate",
      "title": "Mother of slain student wins case against her roommate",
      "court": "Supreme People's Court / People's Courts",
      "date": "2022-01-11",
      "citation": "",
      "docket": "",
      "url": "https://english.court.gov.cn/2022-01/11/c_761843.htm",
      "source": "Supreme People's Court English Typical Cases",
      "authority_level": "guiding_or_typical_case"
    },
    {
      "id": "mainland-china-one-sentenced-in-epidemic-related-fraud-case-in-shanghai",
      "title": "One sentenced in epidemic-related fraud case in Shanghai",
      "court": "Supreme People's Court / People's Courts",
      "date": "2020-03-04",
      "citation": "",
      "docket": "",
      "url": "https://english.court.gov.cn/2020-03/04/c_761900.htm",
      "source": "Supreme People's Court English Typical Cases",
      "authority_level": "guiding_or_typical_case"
    },
    {
      "id": "mainland-china-osteoarthritis-treatment-ip-case-solved-in-court",
      "title": "Osteoarthritis treatment IP case solved in court",
      "court": "Supreme People's Court / People's Courts",
      "date": "2024-12-06",
      "citation": "",
      "docket": "",
      "url": "https://english.court.gov.cn/2024-12/06/c_1051210.htm",
      "source": "Supreme People's Court English Typical Cases",
      "authority_level": "guiding_or_typical_case"
    },
    {
      "id": "mainland-china-spc-s-circuit-court-hears-civil-cases-on-online-mobile-platform",
      "title": "SPC’s circuit court hears civil cases on online mobile platform",
      "court": "Supreme People's Court / People's Courts",
      "date": "2020-03-23",
      "citation": "",
      "docket": "",
      "url": "https://english.court.gov.cn/2020-03/23/c_761881.htm",
      "source": "Supreme People's Court English Typical Cases",
      "authority_level": "guiding_or_typical_case"
    },
    {
      "id": "mainland-china-spc-s-third-circuit-court-concludes-foreign-related-commercial-case-online",
      "title": "SPC’s Third Circuit Court concludes foreign-related commercial case online",
      "court": "Supreme People's Court / People's Courts",
      "date": "2020-03-31",
      "citation": "",
      "docket": "",
      "url": "https://english.court.gov.cn/2020-03/31/c_761911.htm",
      "source": "Supreme People's Court English Typical Cases",
      "authority_level": "guiding_or_typical_case"
    },
    {
      "id": "mainland-china-taiwan-academic-gets-jail-time-for-espionage",
      "title": "Taiwan academic gets jail time for espionage",
      "court": "Supreme People's Court / People's Courts",
      "date": "2020-11-26",
      "citation": "",
      "docket": "",
      "url": "https://english.court.gov.cn/2020-11/26/c_761812.htm",
      "source": "Supreme People's Court English Typical Cases",
      "authority_level": "guiding_or_typical_case"
    },
    {
      "id": "mainland-china-transnational-trial-heard-online-amid-epidemic",
      "title": "Transnational trial heard online amid epidemic",
      "court": "Supreme People's Court / People's Courts",
      "date": "2020-03-11",
      "citation": "",
      "docket": "",
      "url": "https://english.court.gov.cn/2020-03/11/c_761878.htm",
      "source": "Supreme People's Court English Typical Cases",
      "authority_level": "guiding_or_typical_case"
    }
  ],
  "candidate_ids": [
    "mainland-china-cases-of-judicial-protection-for-intellectual-property-rights-in-seed-industry-by-the-people-s-courts-of-",
    "mainland-china-case-of-yi-redacted-s-illegal-introduction-of-invasive-alien-species-judicial-determination-of-the-crime-",
    "mainland-china-guiding-case-no-257",
    "mainland-china-guiding-case-no-215",
    "mainland-china-guiding-case-no-214",
    "mainland-china-guiding-case-no-177",
    "mainland-china-guiding-case-no-236",
    "mainland-china-guiding-case-no-235",
    "mainland-china-guiding-case-no-233",
    "mainland-china-guiding-case-no-232",
    "mainland-china-guiding-case-no-231",
    "mainland-china-guiding-case-no-229",
    "mainland-china-guiding-case-no-224",
    "mainland-china-guiding-case-no-217",
    "mainland-china-guiding-case-no-115",
    "mainland-china-guiding-case-no-223",
    "mainland-china-guiding-case-no-220",
    "mainland-china-guiding-case-no-219",
    "mainland-china-guiding-case-no-162",
    "mainland-china-guiding-case-no-159",
    "mainland-china-osteoarthritis-treatment-ip-case-solved-in-court",
    "mainland-china-ningbo-maritime-court-hailed-for-efficient-resolution-of-maritime-dispute",
    "mainland-china-nation-advances-in-protection-of-tech-related-ip",
    "mainland-china-luxury-ban-prompts-repayment-a-decade-after-ruling-was-made",
    "mainland-china-dutch-collector-ordered-to-return-buddha-statue",
    "mainland-china-man-sentenced-to-death-for-murder-of-ex-girlfriend",
    "mainland-china-man-gets-18-months-in-prison-for-indecent-acts-against-alibaba-employee",
    "mainland-china-law-equalizes-compensation-for-rural-urban-accident-victims",
    "mainland-china-firm-owner-jailed-for-illegal-drug-dumping",
    "mainland-china-court-orders-divorced-mother-to-live-with-educate-8-year-old-daughter",
    "mainland-china-mother-of-slain-student-wins-case-against-her-roommate",
    "mainland-china-father-girlfriend-get-death-sentence-for-killing-children",
    "mainland-china-chinese-court-holds-trial-in-absentia-of-embezzlement-fugitive",
    "mainland-china-relics-protection-efforts-deliver-results",
    "mainland-china-subtitle-website-founder-jailed-for-film-piracy",
    "mainland-china-woman-sentenced-to-death-for-series-of-killings",
    "mainland-china-26-year-old-matricide-seeks-to-appeal-death-sentence",
    "mainland-china-court-rejects-claim-against-livestream-host",
    "mainland-china-court-rejects-appeal-by-canadian-drug-smuggler",
    "mainland-china-china-court-issues-first-ruling-on-personal-bankruptcy",
    "mainland-china-environment-cases-benefit-from-it-use",
    "mainland-china-wrongfully-jailed-man-gets-more-compensation-for-his-mental-anguish",
    "mainland-china-serial-killer-and-rapist-executed-in-hebei",
    "mainland-china-death-sentence-for-ex-con-who-fatally-injured-senior",
    "mainland-china-ex-huarong-chairman-executed-for-corruption",
    "mainland-china-man-cleared-of-rape-conviction-compensated",
    "mainland-china-woman-who-hid-covid-19-condition-on-flight-gets-prison-with-reprieve",
    "mainland-china-death-sentence-for-ex-huarong-chief-reasonable-experts-say",
    "mainland-china-man-who-raped-girl-gets-death-penalty-after-retrial",
    "mainland-china-man-who-raped-girl-gets-death-sentence-at-retrial",
    "mainland-china-chinese-court-rules-hydropower-company-to-protect-rare-plant",
    "mainland-china-hospital-ordered-to-pay-760-000-to-family-in-baby-mix-up-case",
    "mainland-china-court-orders-return-of-stolen-zhang-gong-patriarch-statue",
    "mainland-china-man-who-killed-schoolboys-executed",
    "mainland-china-man-sentenced-to-death-for-raping-4-year-old",
    "mainland-china-taiwan-academic-gets-jail-time-for-espionage",
    "mainland-china-retrial-set-for-3-who-confessed-to-abuse-that-led-to-woman-s-death",
    "mainland-china-ex-party-chief-of-hohhot-sentenced",
    "mainland-china-gang-leader-sentenced-to-death-in-qinghai",
    "mainland-china-court-sentences-23-organized-crime-gang-members-to-prison",
    "mainland-china-nine-sentenced-to-jail-over-counterfeiting-lego-toys",
    "mainland-china-former-official-gets-six-year-prison-term",
    "mainland-china-beijing-court-sentences-counterfeit-merchant",
    "mainland-china-china-s-hunan-punishes-defendants-for-mafia-style-crimes",
    "mainland-china-real-estate-firm-founder-gets-jail-time-for-molesting-child",
    "mainland-china-former-hainan-judge-pleads-guilty-to-bribery",
    "mainland-china-special-court-instituted-in-china-s-qinghai-to-hear-environmental-cases",
    "mainland-china-man-sentenced-to-one-year-in-jail-for-poaching-rare-fish",
    "mainland-china-man-who-murdered-wife-hid-body-executed-in-shanghai",
    "mainland-china-court-ruling-clarifies-need-to-regulate-activities-of-online-video-platforms",
    "mainland-china-henan-man-files-for-compensation-over-wrongful-detention",
    "mainland-china-court-lightens-sentences-in-generic-cancer-drug-case",
    "mainland-china-top-court-to-review-child-rapist-s-reduced-sentence",
    "mainland-china-top-court-to-review-high-profile-change-in-s-china-death-penalty-case",
    "mainland-china-clarity-sought-on-court-ruling-against-two-workers-who-refused-overtime",
    "mainland-china-spc-s-ip-arm-hears-administrative-case-over-invalidated-patent",
    "mainland-china-spc-s-ip-arm-hears-copyright-dispute-over-computer-software-online",
    "mainland-china-spc-s-online-trial-platform-allows-witnesses-to-testify-remotely",
    "mainland-china-28-sentenced-in-deadly-tower-collapse",
    "mainland-china-child-visitations-ensured-in-cloud",
    "mainland-china-spc-s-2nd-circuit-court-hears-appeal-online",
    "mainland-china-returnee-who-hid-travels-violated-virus-control-rules-imprisoned",
    "mainland-china-rulings-on-9-officials-linked-to-schoolyard-burial-upheld",
    "mainland-china-henan-villager-jailed-for-over-15-yrs-vindicated-in-retrial",
    "mainland-china-china-publishes-typical-bankruptcy-reorganization-compromise-cases",
    "mainland-china-court-rules-over-260-000-in-compensation-after-high-rise-apartment-incident",
    "mainland-china-spc-s-third-circuit-court-concludes-foreign-related-commercial-case-online",
    "mainland-china-spc-s-circuit-court-hears-civil-cases-on-online-mobile-platform",
    "mainland-china-chinese-woman-handed-7-year-sentence-for-smuggling-pangolin-scales",
    "mainland-china-mafia-kingpin-sentenced-to-death-in-hainan",
    "mainland-china-transnational-trial-heard-online-amid-epidemic",
    "mainland-china-man-sentenced-to-8-year-jail-for-illegal-wildlife-trade",
    "mainland-china-spc-conducts-mediation-through-online-program",
    "mainland-china-spc-carries-out-first-online-mobile-hearing-amid-epidemic",
    "mainland-china-one-sentenced-in-epidemic-related-fraud-case-in-shanghai",
    "mainland-china-man-sentenced-to-8-month-imprisonment-for-hunting-endangered-wildlife",
    "mainland-china-chinese-man-sentenced-for-illegal-wildlife-hunting",
    "mainland-china-high-profile-criminal-executed-after-ruling-from-top-court",
    "mainland-china-death-penalty-for-man-who-killed-doctor-upheld"
  ]
}